fridrich/__init__.py
fridrich/classes.py
fridrich/cryption_tools.py
fridrich/errors.py
fridrich/file_transfer.py
fridrich/backend/__init__.py
fridrich/backend/debugging.py
fridrich/server/__init__.py
fridrich/server/accounts.py
fridrich/server/app_store.py
fridrich/server/classes.py
fridrich/server/server_funcs.py
fridrich/server/user_tools.py
fridrich/server/w_station_funcs.py
fridrich-1.1.3.dist-info/LICENSE
fridrich-1.1.3.dist-info/METADATA
fridrich-1.1.3.dist-info/WHEEL
fridrich-1.1.3.dist-info/top_level.txt
fridrich-1.1.3.dist-info/RECORD
