Metadata-Version: 2.1
Name: fridrich
Version: 1.1.3
Summary: packs all fridrich functions in one package
Home-page: https://github.com/Nilusink/Fridrich
Author: Nilusink
Author-email: nilusink@protonmail.com
License: UNKNOWN
Project-URL: Official Website, http://info.fridrich.xyz
Platform: UNKNOWN
Classifier: Programming Language :: Python :: 3.10
Classifier: License :: OSI Approved :: MIT License
Classifier: Operating System :: OS Independent
Requires-Python: >=3.10
License-File: LICENSE
